vaticinator/__init__.py
vaticinator/cli.py
vaticinator/fortune_file.py
vaticinator/vaticinator.py
vaticinator/version.py
vaticinator-0.1.0.dist-info/licenses/LICENSE
vaticinator-0.1.0.dist-info/METADATA
vaticinator-0.1.0.dist-info/WHEEL
vaticinator-0.1.0.dist-info/entry_points.txt
vaticinator-0.1.0.dist-info/top_level.txt
vaticinator-0.1.0.dist-info/RECORD
