Metadata-Version: 2.4
Name: vaticinator
Version: 0.1.0
Summary: Yet another Python fortune implementation
Home-page: https://github.com/hazelmollusk/vaticinator
Author: Matt Barry
Author-email: matt@hazelmollusk.org
License: MIT
Project-URL: webpage, https://github.com/hazelmollusk/vaticinator
Project-URL: Documentation, https://vaticinator.readthedocs.io/en/latest/
Project-URL: Changelog, https://github.com/hazelmollusk/vaticinator/blob/main/CHANGELOG.rst
Project-URL: Issue Tracker, https://github.com/hazelmollusk/vaticinator/issues
Project-URL: Discussion Forum, https://github.com/hazelmollusk/vaticinator/discussions
Keywords: fortune,games
Classifier: Development Status :: 4 - Beta
Classifier: License :: OSI Approved :: GNU General Public License v2 (GPLv2)
Classifier: Intended Audience :: System Administrators
Classifier: Natural Language :: English
Classifier: Operating System :: POSIX
Classifier: Programming Language :: Python :: 3.11
Classifier: Topic :: Games/Entertainment :: Fortune Cookies
Requires-Python: >=3.11, <4
License-File: LICENSE
Dynamic: author
Dynamic: author-email
Dynamic: classifier
Dynamic: description
Dynamic: description-content-type
Dynamic: home-page
Dynamic: keywords
Dynamic: license
Dynamic: license-file
Dynamic: project-url
Dynamic: requires-python
Dynamic: summary
